create_nb_app/__init__.py
create_nb_app/cli.py
create_nb_app/config.py
create_nb_app/scaffolder.py
create_nb_app-0.1.2.dist-info/LICENCE
create_nb_app-0.1.2.dist-info/METADATA
create_nb_app-0.1.2.dist-info/WHEEL
create_nb_app-0.1.2.dist-info/entry_points.txt
create_nb_app-0.1.2.dist-info/top_level.txt
create_nb_app-0.1.2.dist-info/RECORD
