Metadata-Version: 2.2
Name: create-nb-app
Version: 0.1.2
Summary: An oppinionated CLI for creating typesafe Python projects.
Home-page: https://github.com/nikolaiborbe/create-nb-app
Author: Nikolai G. Borbe
Author-email: nikolaiborbe@gmail.com
Classifier: Programming Language :: Python :: 3
Classifier: License :: OSI Approved :: MIT License
License-File: LICENCE
Requires-Dist: questionary
Dynamic: author
Dynamic: author-email
Dynamic: classifier
Dynamic: description
Dynamic: description-content-type
Dynamic: home-page
Dynamic: requires-dist
Dynamic: summary
